claude_skills_mcp_backend/__init__.py
claude_skills_mcp_backend/__main__.py
claude_skills_mcp_backend/config.py
claude_skills_mcp_backend/http_server.py
claude_skills_mcp_backend/mcp_handlers.py
claude_skills_mcp_backend/scheduler.py
claude_skills_mcp_backend/search_engine.py
claude_skills_mcp_backend/skill_loader.py
claude_skills_mcp_backend/state_manager.py
claude_skills_mcp_backend/update_checker.py
claude_skills_mcp_backend-1.0.6.dist-info/METADATA
claude_skills_mcp_backend-1.0.6.dist-info/WHEEL
claude_skills_mcp_backend-1.0.6.dist-info/entry_points.txt
claude_skills_mcp_backend-1.0.6.dist-info/RECORD
