Metadata-Version: 2.4
Name: claude-skills-mcp-backend
Version: 1.0.6
Summary: Heavy backend for Claude Skills MCP server with vector search (Streamable HTTP)
Project-URL: Homepage, https://github.com/K-Dense-AI/claude-skills-mcp
Project-URL: Documentation, https://github.com/K-Dense-AI/claude-skills-mcp/blob/main/packages/backend/README.md
Project-URL: Repository, https://github.com/K-Dense-AI/claude-skills-mcp
Project-URL: Bug Tracker, https://github.com/K-Dense-AI/claude-skills-mcp/issues
Author-email: K-Dense AI <orion.li@k-dense.ai>
Maintainer-email: K-Dense AI <orion.li@k-dense.ai>
License: Apache-2.0
Keywords: agent,ai,backend,claude,mcp,scientific,skills,vector-search
Classifier: Development Status :: 4 - Beta
Classifier: Intended Audience :: Developers
Classifier: Intended Audience :: Science/Research
Classifier: License :: OSI Approved :: Apache Software License
Classifier: Programming Language :: Python :: 3.12
Classifier: Topic :: Scientific/Engineering :: Artificial Intelligence
Requires-Python: <3.13,>=3.12
Requires-Dist: httpx>=0.24.0
Requires-Dist: mcp>=1.0.0
Requires-Dist: numpy>=1.24.0
Requires-Dist: sentence-transformers>=2.2.0
Requires-Dist: starlette>=0.27.0
Requires-Dist: torch<3.0.0,>=2.0.0; platform_system == 'Linux'
Requires-Dist: torch>=2.0.0; platform_system != 'Linux'
Requires-Dist: uvicorn>=0.23.0
Provides-Extra: test
Requires-Dist: pytest-asyncio>=0.21.0; extra == 'test'
Requires-Dist: pytest-cov>=4.1.0; extra == 'test'
Requires-Dist: pytest>=7.4.0; extra == 'test'
